{
  "title": "ელენე ახვლედიანი",
  "prompt_html": "<p>ყურადღებით წაიკითხეთ ქვემოთ მოცემული ტექსტი. გაასწორეთ მორფოლოგიურ-ორთოგრაფიული, სინტაქსური, პუნქტუაციური შეცდომები და სტილისტიკური ხარვეზები ისე, რომ ტექსტის შინაარსი არ შეცვალოთ. ტექსტი ჩაასწორე უშუალოდ ველში — დასრულების შემდეგ იხილავ სწორ ვარიანტსა და თითოეული შესწორების ახსნას.</p>",
  "buckets": [
    {
      "key": "lang",
      "label": "მორფ.-ორთოგრაფია, სინტაქსი",
      "max": 8
    },
    {
      "key": "style",
      "label": "სტილისტიკა და სიზუსტე",
      "max": 2
    },
    {
      "key": "punct",
      "label": "პუნქტუაცია",
      "max": 6
    }
  ],
  "segments": [
    {
      "t": "ცნობილი ქართველი მხატვარი ელენე ახვლედიანი 1901 წელს დაიბადა თელავში. იგი ჯერ სამხატვრო სტუდიაში "
    },
    {
      "c": "c1"
    },
    {
      "t": " 1922 წელს კი თბილისის სამხატვრო აკადემიაში ჩაირიცხა. აკადემიის ხელმძღვანელობამ წარჩინებული სტუდენტი საზღვარგარეთ გაგზავნა და მან სწავლა განაგრძო პარიზში, "
    },
    {
      "c": "c2"
    },
    {
      "t": " კოლაროსის აკადემიაში. პარიზში გაიმართა მისი პირველი პერსონალური გამოფენა. "
    },
    {
      "c": "c3"
    },
    {
      "t": " რომ "
    },
    {
      "c": "c4"
    },
    {
      "t": " ერთად ეს გამოფენა მოუნახულებია პიკასოს, "
    },
    {
      "c": "c5"
    },
    {
      "t": " განსაკუთრებით "
    },
    {
      "c": "c6"
    },
    {
      "t": " ფერწერული ტილო „კახეთი, ზამთარი“. ელენე ახვლედიანმა მნიშვნელოვანი წვლილი შეიტანა ქართული პეიზაჟური ფერწერის განვითარებაში. "
    },
    {
      "c": "c7"
    },
    {
      "c": "c7b"
    },
    {
      "t": " რომელთაგან გამოირჩევა თბილისის, სიღნაღისა და თელავის პეიზაჟები. განსაკუთრებული იყო ელენე ახვლედიანის დამოკიდებულება "
    },
    {
      "c": "c8"
    },
    {
      "t": ". როგორც მისი თანამედროვეები "
    },
    {
      "c": "c9"
    },
    {
      "t": " "
    },
    {
      "c": "c10"
    },
    {
      "t": " უშუალო ჩარევის შედეგად არაერთი ძველი შენობა გადაურჩა დანგრევას. ელენე ახვლედიანი მთელი სიცოცხლის განმავლობაში ემსახურებოდა "
    },
    {
      "c": "c11"
    },
    {
      "t": " სცენოგრაფიის განვითარებას. მან სამოცდაათზე მეტი სპექტაკლი გააფორმა როგორც "
    },
    {
      "c": "c12"
    },
    {
      "t": " ისე მის ფარგლებს გარეთ. იგი ასევე "
    },
    {
      "c": "c13"
    },
    {
      "t": " თანამშრომლობდა გამომცემლობებთან. ელენე ახვლედიანის საუკეთესო გრაფიკული ნამუშევრებია ვაჟა-ფშაველას მოთხრობებისა და პოემების ილუსტრაციები."
    }
  ],
  "corrections": {
    "c1": {
      "original": "სწავლობდა",
      "corrected": "სწავლობდა,",
      "category": "punct",
      "points": 1,
      "why_html": "<p>ერთმანეთს უპირისპირდება ორი დამოუკიდებელი წინადადება — „იგი ჯერ … სწავლობდა“ და „1922 წელს კი … ჩაირიცხა“, — დაკავშირებული მაპირისპირებელი ნაწილაკით „კი“. ასეთ წინადადებებს შორის მძიმე იწერება, ე. ი. სიტყვა „სწავლობდა“-ს შემდეგ.</p>"
    },
    "c2": {
      "original": "კერძოდ",
      "corrected": "კერძოდ,",
      "category": "punct",
      "points": 1,
      "why_html": "<p>„კერძოდ“ დამაზუსტებელი (განმმარტებელი) სიტყვაა — შემოაქვს წინამავალის („პარიზში“) დაზუსტება. ასეთი ჩართული სიტყვა ორივე მხრიდან მძიმით გამოიყოფა, ამიტომ მძიმე იწერება „კერძოდ“-ის შემდეგაც: „განაგრძო პარიზში, კერძოდ, კოლაროსის აკადემიაში“.</p>"
    },
    "c3": {
      "original": "ცნობილია",
      "corrected": "ცნობილია,",
      "category": "punct",
      "points": 1,
      "why_html": "<p>დამოკიდებული საქვემდებარო წინადადება შემოდის კავშირით „რომ“. მთავარ წინადადებას („ცნობილია“) დამოკიდებულისგან მძიმე მიჯნავს, ამიტომ მძიმე იწერება „რომ“-ის წინ.</p>"
    },
    "c4": {
      "original": "მრავალ სხვა დამთვალიერებლებთან",
      "corrected": "მრავალ სხვა დამთვალიერებელთან",
      "category": "morph",
      "points": 1,
      "why_html": "<p>რიცხვის შეთანხმების შეცდომაა. რაოდენობითი მსაზღვრელის („მრავალ“) შემდეგ საზღვრული სახელი მხოლობით რიცხვში დგას: „მრავალ … დამთვალიერებელთან“. მრავლობითი ფორმა „დამთვალიერებლებთან“ მცდარია — ქართულში რიცხვით/რაოდენობით განსაზღვრული საგანი მხოლობითში რჩება.</p>"
    },
    "c5": {
      "original": "ვისაც",
      "corrected": "რომელსაც",
      "category": "style",
      "points": 1,
      "why_html": "<p>ლექსიკურ-სტილისტური უზუსტობაა. ნაცვალსახელი „ვინ/ვისაც“ პირს (ადამიანს) მიემართება, საგანს კი — „რომელი/რომელსაც“. აქ მისართითი წევრი ნივთია — ფერწერული ტილო, ამიტომ სწორია „რომელსაც … მოსწონებია“, და არა „ვისაც“.</p>"
    },
    "c6": {
      "original": "მოწონებია",
      "corrected": "მოსწონებია",
      "category": "orth",
      "points": 1,
      "why_html": "<p>მორფოლოგიურ-ორთოგრაფიული შეცდომაა. ზმნის სწორი ფორმაა „მოსწონებია“ — ფუძეში ჩნდება თანხმოვანი „ს“ (მო-ს-წონ-). ფორმა „მოწონებია“ (უ-ს-ოდ) მცდარია.</p>"
    },
    "c7": {
      "original": "მისი ნამუშევრები იმთავითვე შედევრებად აღიარეს კრიტიკოსებმა და ხელოვნების მოყვარულებმა",
      "corrected": "კრიტიკოსებმა და ხელოვნების მოყვარულებმა იმთავითვე შედევრებად აღიარეს მისი ნამუშევრები",
      "category": "syntax",
      "points": 1,
      "why_html": "<p>წინადადების ბუნებრივი წყობით მოქმედი სუბიექტი („კრიტიკოსებმა და ხელოვნების მოყვარულებმა\") წინ უნდა იდგეს.</p>"
    },
    "c8": {
      "original": "ძველ თბილისთან მიმართებაში",
      "corrected": "ძველი თბილისის მიმართ",
      "category": "syntax",
      "points": 1,
      "why_html": "<p>დარღვეულია მსაზღვრელ-საზღვრულის შეთანხმება და ბრუნვის მართვა. სწორი ფორმაა „ძველი თბილისის მიმართ“: მსაზღვრელი „ძველი“ ნათესაობითში არ იკვეცება, საზღვრული „თბილისის“ ნათესაობითშია, თანდებული კი — „მიმართ“. ფორმა „ძველ თბილისთან მიმართებაში“ მცდარია.</p>"
    },
    "c9": {
      "original": "იხსენებდნენ",
      "corrected": "იხსენებდნენ,",
      "category": "punct",
      "points": 1,
      "why_html": "<p>წინადადება იწყება შედარებით-განმმარტებელი დამოკიდებული წინადადებით („როგორც მისი თანამედროვეები იხსენებდნენ“), რომელიც მთავარ ნაწილს მძიმით უნდა გაემიჯნოს. მძიმე იწერება დამოკიდებულის ბოლოს, სიტყვა „იხსენებდნენ“-ის შემდეგ.</p>"
    },
    "c10": {
      "original": "მხატვარის",
      "corrected": "მხატვრის",
      "category": "orth",
      "points": 1,
      "why_html": "<p>ორთოგრაფიულ-მორფოლოგიური (სინკოპის) შეცდომაა. სიტყვა „მხატვარი“ ნათესაობით ბრუნვაში კარგავს ფუძისეულ ხმოვან „ა“-ს: მხატვარი → მხატვრის. ფორმა „მხატვარის“ მცდარია; სწორია „მხატვრის უშუალო ჩარევის შედეგად“.</p>"
    },
    "c11": {
      "original": "ქართულ",
      "corrected": "ქართული",
      "category": "syntax",
      "points": 1,
      "why_html": "<p>მსაზღვრელ-საზღვრულის შეთანხმების დარღვევაა. ნათესაობით ბრუნვაში (-ის) წინმავალი ზედსართავი მსაზღვრელი არ იკვეცება და -ი ბოლოსართს ინარჩუნებს: „ქართული სცენოგრაფიის“. კვეცილი ფორმა „ქართულ“ აქ მცდარია.</p>"
    },
    "c12": {
      "original": "საქართველოში",
      "corrected": "საქართველოში,",
      "category": "punct",
      "points": 1,
      "why_html": "<p>გამეორებადი (წყვილადი) მაერთებელი კავშირი „როგორც … ისე …“ აერთებს ერთგვაროვან წევრებს. მისი მეორე ნაწილის — „ისე“-ს — წინ მძიმე იწერება: „როგორც საქართველოში, ისე მის ფარგლებს გარეთ“.</p>"
    },
    "c13": {
      "original": "ნაყოფიერათ",
      "corrected": "ნაყოფიერად",
      "category": "orth",
      "points": 1,
      "why_html": "<p>მორფოლოგიურ-ორთოგრაფიული შეცდომაა. ვითარებითი ბრუნვის (ზმნისართის) ნიშანი არის -ად და არა -ათ, ამიტომ სწორი ფორმაა „ნაყოფიერად“ (ნაყოფიერად თანამშრომლობდა).</p>"
    },
    "c7b": {
      "original": "",
      "corrected": ",",
      "category": "punct",
      "points": 1,
      "why_html": "<p>განსაზღვრებითი დამოკიდებული წინადადება („რომელთაგან…\") მძიმით გამოიყოფა.</p>"
    }
  }
}